grepurl.py
grepurl-0.2.0.dist-info/METADATA
grepurl-0.2.0.dist-info/WHEEL
grepurl-0.2.0.dist-info/entry_points.txt
grepurl-0.2.0.dist-info/top_level.txt
grepurl-0.2.0.dist-info/RECORD
