Metadata-Version: 2.1
Name: grepurl
Version: 0.2.0
Summary: extract URLs from websites or local HTML files
Home-page: https://github.com/arne-cl/grepurl
Author: Arne Neumann
Maintainer-email: grepurl.programming@arne.cl
License: GPLv2 or later
Platform: UNKNOWN
Requires-Dist: beautifulsoup4
Requires-Dist: requests
